spyder_reports/__init__.py
spyder_reports/_version.py
spyder_reports/reportsplugin.py
spyder_reports/tests/__init__.py
spyder_reports/tests/test_plugin.py
spyder_reports/utils/__init__.py
spyder_reports/utils/templates/welcome.md
spyder_reports/widgets/__init__.py
spyder_reports/widgets/reportsgui.py
spyder_reports/widgets/tests/__init__.py
spyder_reports/widgets/tests/test_report_widget.py
spyder_reports-0.1.1.dist-info/DESCRIPTION.rst
spyder_reports-0.1.1.dist-info/METADATA
spyder_reports-0.1.1.dist-info/RECORD
spyder_reports-0.1.1.dist-info/WHEEL
spyder_reports-0.1.1.dist-info/metadata.json
spyder_reports-0.1.1.dist-info/top_level.txt
