Metadata-Version: 2.0
Name: spyder-reports
Version: 0.1.1
Summary: Spyder-IDE plugin for Markdown reports using Pweave.
Home-page: https://github.com/spyder-ide/spyder-ide
Author: Spyder Project Contributors
Author-email: admin@spyder-ide.org
License: MIT
Keywords: Spyder,Plugin
Platform: UNKNOWN
Classifier: Development Status :: 4 - Beta
Classifier: Intended Audience :: Developers
Classifier: Intended Audience :: Science/Research
Classifier: License :: OSI Approved :: MIT License
Classifier: Operating System :: MacOS
Classifier: Operating System :: Microsoft :: Windows
Classifier: Operating System :: POSIX :: Linux
Classifier: Programming Language :: Python :: 2.7
Classifier: Programming Language :: Python :: 3.5
Classifier: Programming Language :: Python :: 3.6
Requires-Dist: matplotlib
Requires-Dist: pweave
Requires-Dist: spyder (>=3.2.0)
